deepnight/__init__.py
deepnight/_globals.py
deepnight/audio.py
deepnight/chat.py
deepnight/completions.py
deepnight/config.py
deepnight/embeddings.py
deepnight/errors.py
deepnight-0.1.3.2.dist-info/METADATA
deepnight-0.1.3.2.dist-info/WHEEL
deepnight-0.1.3.2.dist-info/top_level.txt
deepnight-0.1.3.2.dist-info/RECORD
