Metadata-Version: 2.1
Name: deepnight
Version: 0.1.3.2
Requires-Dist: requests
